protopie/__init__.py
protopie/ast.py
protopie/errors.py
protopie/grammar.py
protopie/lalr.py
protopie/lexer.py
protopie/parser.py
protopie/py.typed
protopie/spans.py
protopie/symbol.py
protopie-0.1.0.dist-info/METADATA
protopie-0.1.0.dist-info/WHEEL
protopie-0.1.0.dist-info/licenses/LICENSE
protopie-0.1.0.dist-info/RECORD
