Metadata-Version: 2.4
Name: protopie
Version: 0.1.0
Summary: Protobuf proto3 syntax parser
Project-URL: Repository, https://github.com/maralla/protopie
Author: maralla
License: MIT License
License-File: LICENSE
Keywords: parser,proto3,protobuf
Classifier: Development Status :: 3 - Alpha
Classifier: Intended Audience :: Developers
Classifier: License :: OSI Approved :: MIT License
Classifier: Programming Language :: Python :: 3
Classifier: Programming Language :: Python :: 3 :: Only
Classifier: Topic :: Software Development :: Compilers
Requires-Python: >=3.14
